lisagwresponse/__init__.py
lisagwresponse/psd.py
lisagwresponse/response.py
lisagwresponse/stochastic.py
lisagwresponse/utils.py
lisagwresponse-3.0.2.dist-info/METADATA
lisagwresponse-3.0.2.dist-info/WHEEL
lisagwresponse-3.0.2.dist-info/licenses/LICENSE
lisagwresponse-3.0.2.dist-info/RECORD
