Metadata-Version: 2.4
Name: lisagwresponse
Version: 3.0.2
Summary: Compute the LISA link responses to gravitational waves in the time domain
License: BSD 3-Clause
License-File: LICENSE
Keywords: LISA,response function,simulation
Author: Jean-Baptiste Bayle
Author-email: j2b.bayle@gmail.com>
Maintainer: Jean-Baptiste Bayle
Maintainer-email: j2b.bayle@gmail.com>
Requires-Python: >=3.12,<4.0
Classifier: Intended Audience :: Science/Research
Classifier: Topic :: Scientific/Engineering :: Astronomy
Classifier: Topic :: Scientific/Engineering :: Physics
Requires-Dist: h5py (>=3.12.1,<4.0.0)
Requires-Dist: healpy (>=1.17.3,<2.0.0)
Requires-Dist: importlib-metadata (>=8.5.0,<9.0.0)
Requires-Dist: lisaconstants (>=2.0.1,<3.0.0)
Requires-Dist: matplotlib (>=3.9.2,<4.0.0)
Requires-Dist: numpy (>=2.1.2,<3.0.0)
Requires-Dist: scipy (>=1.14.1,<2.0.0)
Project-URL: Documentation, https://lisa-simulation.pages.in2p3.fr/gw-response
Project-URL: Download, https://gitlab.in2p3.fr/lisa-simulation/gw-response/-/releases
Project-URL: Issue Tracker, https://gitlab.in2p3.fr/lisa-simulation/gw-response/-/issues
Project-URL: Repository, https://gitlab.in2p3.fr/lisa-simulation/gw-response
